hello_rust_pyo3-0.1.0.dist-info/METADATA
hello_rust_pyo3-0.1.0.dist-info/WHEEL
hello_rust_pyo3/__init__.py
hello_rust_pyo3/hello_rust_pyo3.cp39-win_amd64.pyd
hello_rust_pyo3-0.1.0.dist-info/RECORD
