Metadata-Version: 2.4
Name: hello-rust-pyo3
Version: 0.1.0
Classifier: Programming Language :: Python :: 3
Classifier: Programming Language :: Rust
Classifier: License :: OSI Approved :: MIT License
Classifier: Operating System :: OS Independent
Summary: Small example of a Rust extension module for Python using PyO3 + maturin.
Author-email: Your Name <you@example.com>
License: MIT
Requires-Python: >=3.8
Project-URL: Homepage, https://example.com/hello-rust-pyo3
